{"cameraMode":{"drawMode":0,"name":"Shaded","section":"Shading Mode"},"sceneLighting":true,"audioPlay":false,"sceneViewState":{"m_AlwaysRefresh":false,"showFog":true,"showSkybox":true,"showFlares":true,"showImageEffects":true,"showParticleSystems":true,"showVisualEffectGraphs":true,"m_FxEnabled":true},"in2DMode":false,"pivot":{"x":12.822761535644532,"y":47.14305114746094,"z":8.611181259155274},"rotation":{"x":0.36629748344421389,"y":-0.14096923172473908,"z":0.06037916615605354,"w":0.9186664819717407},"size":10.0,"orthographic":false}